figshare_client/.DS_Store
figshare_client/__init__.py
figshare_client/__main__.py
figshare_client/api.py
figshare_client/cli.py
figshare_client/py.typed
figshare_client/version.py
figshare_client-0.0.3.dist-info/licenses/LICENSE
figshare_client-0.0.3.dist-info/WHEEL
figshare_client-0.0.3.dist-info/entry_points.txt
figshare_client-0.0.3.dist-info/METADATA
figshare_client-0.0.3.dist-info/RECORD
