Metadata-Version: 2.4
Name: figshare_client
Version: 0.0.3
Summary: A client to Figshare
Keywords: snekpack,cookiecutter,figshare
Author: Charles Tapley Hoyt
Author-email: Charles Tapley Hoyt <cthoyt@gmail.com>
License-File: LICENSE
Classifier: Development Status :: 1 - Planning
Classifier: Environment :: Console
Classifier: Intended Audience :: Developers
Classifier: License :: OSI Approved :: MIT License
Classifier: Operating System :: OS Independent
Classifier: Framework :: Pytest
Classifier: Framework :: tox
Classifier: Framework :: Sphinx
Classifier: Natural Language :: English
Classifier: Programming Language :: Python
Classifier: Programming Language :: Python :: 3.10
Classifier: Programming Language :: Python :: 3.11
Classifier: Programming Language :: Python :: 3.12
Classifier: Programming Language :: Python :: 3.13
Classifier: Programming Language :: Python :: 3.14
Classifier: Programming Language :: Python :: 3 :: Only
Classifier: Typing :: Typed
Requires-Dist: pydantic
Requires-Dist: requests
Requires-Dist: pystow
Maintainer: Charles Tapley Hoyt
Maintainer-email: Charles Tapley Hoyt <cthoyt@gmail.com>
Requires-Python: >=3.10
Project-URL: Bug Tracker, https://github.com/cthoyt/figshare-client/issues
Project-URL: Homepage, https://github.com/cthoyt/figshare-client
Project-URL: Repository, https://github.com/cthoyt/figshare-client.git
Project-URL: Documentation, https://figshare_client.readthedocs.io
Project-URL: Funding, https://github.com/sponsors/cthoyt
